YourSuperAPI/YourSuperAPI.py
YourSuperAPI/__init__.py
YourSuperAPI-0.0.3.dist-info/LICENSE
YourSuperAPI-0.0.3.dist-info/METADATA
YourSuperAPI-0.0.3.dist-info/WHEEL
YourSuperAPI-0.0.3.dist-info/top_level.txt
YourSuperAPI-0.0.3.dist-info/RECORD
