Metadata-Version: 2.1
Name: YourSuperAPI
Version: 0.0.3
Summary: Python wrapper for the YourSuper API
Home-page: https://github.com/LukePrior/PythonYourSuperAPI
Author: Luke Prior
Author-email: current.address@unknown.invalid
License: UNKNOWN
Project-URL: Bug Tracker, https://github.com/LukePrior/PythonYourSuperAPI/issues
Platform: UNKNOWN
Classifier: Programming Language :: Python :: 3
Classifier: License :: OSI Approved :: MIT License
Classifier: Operating System :: OS Independent
Requires-Python: >=3
License-File: LICENSE
